androidllinttoglqc/__init__.py
androidllinttoglqc/androidllinttoglqc.py
android_lint_to_glcq-0.1.3.dist-info/LICENSE
android_lint_to_glcq-0.1.3.dist-info/METADATA
android_lint_to_glcq-0.1.3.dist-info/WHEEL
android_lint_to_glcq-0.1.3.dist-info/entry_points.txt
android_lint_to_glcq-0.1.3.dist-info/top_level.txt
android_lint_to_glcq-0.1.3.dist-info/RECORD
