Metadata-Version: 2.1
Name: android-lint-to-glcq
Version: 0.1.3
Summary: Convert android gradle lint outputs to a GitLab valid json code quality result file
Home-page: https://github.com/STFBEE/android-lint-to-glcq
Author: Vlad Onishchenko
Author-email: me@vladonishchenko.ru
License: MIT
Keywords: android,lint,gitlab,report,gradle
Platform: UNKNOWN
Classifier: Development Status :: 2 - Pre-Alpha
Classifier: Intended Audience :: Developers
Classifier: License :: OSI Approved :: MIT License
Classifier: Natural Language :: English
Classifier: Programming Language :: Python :: 2
Classifier: Programming Language :: Python :: 2.6
Classifier: Programming Language :: Python :: 2.7
Classifier: Programming Language :: Python :: 3
Classifier: Programming Language :: Python :: 3.3
Classifier: Programming Language :: Python :: Implementation :: PyPy
License-File: LICENSE
